labinstruments/__init__.py
labinstruments/hittite.py
labinstruments/keithley.py
labinstruments/microlambda.py
SCPI_Lab_Instruments-0.0.1.dist-info/LICENSE.md
SCPI_Lab_Instruments-0.0.1.dist-info/METADATA
SCPI_Lab_Instruments-0.0.1.dist-info/WHEEL
SCPI_Lab_Instruments-0.0.1.dist-info/top_level.txt
SCPI_Lab_Instruments-0.0.1.dist-info/RECORD
