Metadata-Version: 2.1
Name: SCPI-Lab-Instruments
Version: 0.0.1
Summary: Control instruments in the receiver lab over Ethernet using SCPI commands
Home-page: https://github.com/Smithsonian/SCPI-Lab-Instruments
Author: John Garrett
Author-email: john.garrett@cfa.harvard.edu
License: MIT
Project-URL: Changelog, https://github.com/Smithsonian/SCPI-Lab-Instruments/CHANGES.md
Project-URL: Issue Tracker, https://github.com/Smithsonian/SCPI-Lab-Instruments/issues
Keywords: SCPI,Ethernet,Lab equipment,Signal generator,DC power supply
Platform: any
Classifier: Development Status :: 5 - Production/Stable
Classifier: Intended Audience :: Science/Research
Classifier: License :: OSI Approved :: MIT License
Classifier: Natural Language :: English
Classifier: Programming Language :: Python :: 3.5
Classifier: Programming Language :: Python :: 3.6
Classifier: Programming Language :: Python :: 3.7
Classifier: Topic :: Scientific/Engineering
Requires-Dist: sockets
